controme/__init__.py
controme/main.py
controme-0.1.2.dist-info/LICENSE
controme-0.1.2.dist-info/METADATA
controme-0.1.2.dist-info/WHEEL
controme-0.1.2.dist-info/top_level.txt
controme-0.1.2.dist-info/RECORD
