Metadata-Version: 2.1
Name: controme
Version: 0.1.2
Summary: Module to read from controme API Endpoint
Home-page: https://github.com/maxibick/controme
Author: Maximilian Bick
Author-email: maxibick@hotmail.com
Classifier: Development Status :: 3 - Alpha
Classifier: License :: OSI Approved :: MIT License
Classifier: Programming Language :: Python :: 3
Classifier: Programming Language :: Python :: 3.6
Classifier: Programming Language :: Python :: 3.7
Classifier: Programming Language :: Python :: 3.8
License-File: LICENSE
